download_tiktok_no_watermark/download.py
download_tiktok_no_watermark-0.2.8.dist-info/METADATA
download_tiktok_no_watermark-0.2.8.dist-info/WHEEL
download_tiktok_no_watermark-0.2.8.dist-info/top_level.txt
download_tiktok_no_watermark-0.2.8.dist-info/RECORD
